# 反编译文件字节码分析

工具：`javap`、`jclasslib bytecode viewer`、`ASM Bytecode Outline`。

预备知识：".class"文件结构、类加载、栈内存结构。

>运行时数据区中，五大区之一“栈”，是由很多栈帧组成，一个栈帧又可以细分为局部变量表、操作数栈、动态连接、返回地址。
>
>局部变量表：存储方法传入参数和本地临时变量，以及this指针（!!!）。
>
>操作数栈：Java虚拟机的解释执行引擎被称为"基于栈的执行引擎"，其中所指的栈就是指－操作数栈。虚拟机把操作数栈作为它的工作区——大多数指令都要从这里弹出数据，执行运算，然后把结果压回操作数栈，就是作为中间计算数据存储的。

+ `HelloWorld.java`

  ```java
  package org.itstack.demo.javassist;
  
  public class HelloWorld {
      public static void main(String[] args) {
          System.out.println("hi javassist! Greetings from 小傅哥(bugstack.cn)");
      }
  }
  ```

  **`javap -c -p -v` 反编译**：    

  ```
  public class org.itstack.demo.javassist.HelloWorld
    minor version: 0
    major version: 52
    flags: ACC_PUBLIC, ACC_SUPER
  //常量池
  Constant pool:
     #1 = Methodref          #6.#15         // java/lang/Object."<init>":()V
     #2 = Fieldref           #16.#17        // java/lang/System.out:Ljava/io/PrintStream;
     #3 = String             #18            // hi javassist! Greetings from 小傅哥(bugstack.cn)
     #4 = Methodref          #19.#20        // java/io/PrintStream.println:(Ljava/lang/String;)V
     #5 = Class              #21            // org/itstack/demo/javassist/HelloWorld
     #6 = Class              #22            // java/lang/Object
     #7 = Utf8               <init>
     #8 = Utf8               ()V
     #9 = Utf8               Code
    #10 = Utf8               LineNumberTable
    #11 = Utf8               main
    #12 = Utf8               ([Ljava/lang/String;)V
    #13 = Utf8               SourceFile
    #14 = Utf8               HelloWorld.java
    #15 = NameAndType        #7:#8          // "<init>":()V
    #16 = Class              #23            // java/lang/System
    #17 = NameAndType        #24:#25        // out:Ljava/io/PrintStream;
    #18 = Utf8               hi javassist! Greetings from 小傅哥(bugstack.cn)
    #19 = Class              #26            // java/io/PrintStream
    #20 = NameAndType        #27:#28        // println:(Ljava/lang/String;)V
    #21 = Utf8               org/itstack/demo/javassist/HelloWorld
    #22 = Utf8               java/lang/Object
    #23 = Utf8               java/lang/System
    #24 = Utf8               out
    #25 = Utf8               Ljava/io/PrintStream;
    #26 = Utf8               java/io/PrintStream
    #27 = Utf8               println
    #28 = Utf8               (Ljava/lang/String;)V
  {
    //反编译发现这里自动生成了无参构造函数
    public org.itstack.demo.javassist.HelloWorld();
      descriptor: ()V
      flags: ACC_PUBLIC
      Code:
        stack=1, locals=1, args_size=1
           0: aload_0										//把局部变量数组中index=0的值(对象引用，这里是this)加载到操作数栈
           														   //javap没有打印出来局部变量表，但是jclasslib插件可以看到
           1: invokespecial #1                  // Method java/lang/Object."<init>":()V //调用实例方法，即执行常量池中第一个（无参构造方法）
           4: return
        LineNumberTable:
          line 8: 0
  
    public static void main(java.lang.String[]);
      descriptor: ([Ljava/lang/String;)V
      flags: ACC_PUBLIC, ACC_STATIC
      Code:
        stack=2, locals=1, args_size=1
           0: getstatic     #2                  // Field java/lang/System.out:Ljava/io/PrintStream;  从类中获取静态字段
           3: ldc           #3                  // String hi javassist! Greetings from 小傅哥(bugstack.cn)，将常量池中#3数据压入操作数栈
           5: invokevirtual #4                  // Method java/io/PrintStream.println:(Ljava/lang/String;)V 调用对象的实现方法（位于常量池#4处的方法引用）
           8: return
        LineNumberTable:
          line 11: 0
          line 12: 8
  }
  SourceFile: "HelloWorld.java"
  ```

  **`ASM Bytecode Outline` 反编译**：    

  ```
  // class version 52.0 (52)
  // access flags 0x21
  public class org/itstack/demo/javassist/HelloWorld {
  
    // compiled from: HelloWorld.java
  
    // access flags 0x1
    public <init>()V
     L0
      LINENUMBER 8 L0
      ALOAD 0
      INVOKESPECIAL java/lang/Object.<init> ()V
      RETURN
     L1
      LOCALVARIABLE this Lorg/itstack/demo/javassist/HelloWorld; L0 L1 0
      MAXSTACK = 1
      MAXLOCALS = 1
  
    // access flags 0x9
    public static main([Ljava/lang/String;)V
     L0
      LINENUMBER 11 L0
      GETSTATIC java/lang/System.out : Ljava/io/PrintStream;
      LDC "hi javassist! Greetings from \u5c0f\u5085\u54e5(bugstack.cn)"
      INVOKEVIRTUAL java/io/PrintStream.println (Ljava/lang/String;)V
     L1
      LINENUMBER 12 L1
      RETURN
     L2
      LOCALVARIABLE args [Ljava/lang/String; L0 L2 0
      MAXSTACK = 2
      MAXLOCALS = 1
  }
  ```

  

     

​     

​          

​          